makeHelp.py
makeUnits.py
preparePrimeData.py
rpn.py
setup.py
setup_rpn.py
testRPN.py
testRPNWithAlpha.py
unpickle.py
rpn/__init__.py
rpn/factorise.old.py
rpn/factorise.py
rpn/makeHelp.py
rpn/makeUnits.py
rpn/preparePrimeData.py
rpn/profileRPN.py
rpn/rpn.py
rpn/rpn.save.py
rpn/rpnAliases.py
rpn/rpnAstronomy.py
rpn/rpnBase.py
rpn/rpnCalendar.py
rpn/rpnChemistry.py
rpn/rpnCombinatorics.py
rpn/rpnComputer.py
rpn/rpnConstantOperators.py
rpn/rpnConstantUtils.py
rpn/rpnDateTime.py
rpn/rpnDateTimeClass.py
rpn/rpnDebug.py
rpn/rpnDice.py
rpn/rpnEclipse.py
rpn/rpnEstimates.py
rpn/rpnExpression.py
rpn/rpnFactor.py
rpn/rpnGenerator.py
rpn/rpnGeometry.py
rpn/rpnGlobals.py
rpn/rpnInput.py
rpn/rpnKeyboard.py
rpn/rpnLexicographic.py
rpn/rpnList.py
rpn/rpnLocation.py
rpn/rpnLocationClass.py
rpn/rpnMatchUnitTypes.py
rpn/rpnMath.py
rpn/rpnMeasurement.py
rpn/rpnMeasurementClass.py
rpn/rpnModifiers.py
rpn/rpnName.py
rpn/rpnNanoseconds.py
rpn/rpnNumberTheory.py
rpn/rpnOperator.py
rpn/rpnOperators.py
rpn/rpnOutput.py
rpn/rpnPersistence.py
rpn/rpnPhysics.py
rpn/rpnPolynomials.py
rpn/rpnPolytope.py
rpn/rpnPrimeUtils.py
rpn/rpnPrimes.py
rpn/rpnRational.py
rpn/rpnSettings.py
rpn/rpnSpecial.py
rpn/rpnSpecialBase.py
rpn/rpnTestUtils.py
rpn/rpnUnitClasses.py
rpn/rpnUnitTypes.py
rpn/rpnUnits.py
rpn/rpnUtils.py
rpn/rpnValidator.py
rpn/rpnVersion.py
rpn/testConvert.py
rpn/testHelp.py
rpn/testRPN.py
rpn/testRPNWithAlpha.py
rpn/unpickle.py
rpn/rpndata/help.pckl.bz2
rpn/rpndata/unit_conversions.pckl.bz2
rpn/rpndata/unit_help.pckl.bz2
rpn/rpndata/unit_names.pckl.bz2
rpn/rpndata/units.pckl.bz2
rpnChilada-8.5.6.dist-info/LICENSE
rpnChilada-8.5.6.dist-info/METADATA
rpnChilada-8.5.6.dist-info/WHEEL
rpnChilada-8.5.6.dist-info/entry_points.txt
rpnChilada-8.5.6.dist-info/top_level.txt
rpnChilada-8.5.6.dist-info/RECORD
