Metadata-Version: 2.1
Name: rpnChilada
Version: 8.5.6
Summary: command-line RPN calculator
Home-page: http://github.com/ConceptJunkie/rpn/
Author: Rick Gutleber
Author-email: rickg@his.com
License: GPL3
Platform: UNKNOWN
Classifier: Development Status :: 5 - Production/Stable
Classifier: Intended Audience :: End Users/Desktop
Classifier: Natural Language :: English
Classifier: License :: OSI Approved :: GNU General Public License v3 (GPLv3)
Classifier: Operating System :: OS Independent
Classifier: Programming Language :: Python
Classifier: Programming Language :: Python :: 3
Classifier: Programming Language :: Python :: 3.6
Classifier: Programming Language :: Python :: 3.7
Classifier: Programming Language :: Python :: 3.8
Classifier: Programming Language :: Python :: 3.9
Classifier: Topic :: Scientific/Engineering :: Mathematics
Classifier: Environment :: Console
License-File: LICENSE
Requires-Dist: arrow (>=1.2.1)
Requires-Dist: convertdate (>=2.3.2)
Requires-Dist: python-dateutil (>=2.8.2)
Requires-Dist: ephem (>=4.1)
Requires-Dist: ethiopian-date-converter (>=0.1.5)
Requires-Dist: geopy (>=2.2.0)
Requires-Dist: gmpy2 (>=2.0.8)
Requires-Dist: hyperop (>=1.1)
Requires-Dist: importlib-resources (>=5.4.0)
Requires-Dist: mpmath (>=1.2.1)
Requires-Dist: numpy (>=1.19.5)
Requires-Dist: pytz (>=2021.3)
Requires-Dist: rpnChiladaData (>=1.1.0)
Requires-Dist: setuptools (>=56.1.0)
Requires-Dist: skyfield (>=1.40)
Requires-Dist: timezonefinder (>=5.2.0)
Requires-Dist: tzlocal (>=4.1)
Requires-Dist: wheel (>=0.37.0)
